MANIFEST.in
Makefile
README.md
README.rst
requirements.txt
runtests.py
setup.py
Shake_Auth.egg-info/PKG-INFO
Shake_Auth.egg-info/SOURCES.txt
Shake_Auth.egg-info/dependency_links.txt
Shake_Auth.egg-info/not-zip-safe
Shake_Auth.egg-info/requires.txt
Shake_Auth.egg-info/top_level.txt
shake_auth/__init__.py
shake_auth/auth.py
shake_auth/perms.py
shake_auth/utils.py
shake_auth/templates/auth/base.html
shake_auth/templates/auth/change_password.html
shake_auth/templates/auth/email_reset_password.html
shake_auth/templates/auth/reset_password.html
shake_auth/templates/auth/sign_in.html
tests/__init__.py
tests/test_auth.py
tests/test_hashfuncs.py